{
  "image_filename": "CLEVR_new_000628.png",
  "directions": {
    "above": [
      0.0,
      0.0,
      1.0
    ],
    "behind": [
      -0.754490315914154,
      0.6563112735748291,
      0.0
    ],
    "left": [
      -0.6563112735748291,
      -0.7544902563095093,
      0.0
    ],
    "below": [
      -0.0,
      -0.0,
      -1.0
    ],
    "right": [
      0.6563112735748291,
      0.7544902563095093,
      -0.0
    ],
    "front": [
      0.754490315914154,
      -0.6563112735748291,
      -0.0
    ]
  },
  "relationships": {
    "left": [
      [
        1,
        3,
        4
      ],
      [
        4
      ],
      [
        0,
        1,
        3,
        4
      ],
      [
        1,
        4
      ],
      []
    ],
    "front": [
      [
        1,
        3,
        4
      ],
      [
        3
      ],
      [
        0,
        1,
        3,
        4
      ],
      [],
      [
        1,
        3
      ]
    ],
    "right": [
      [
        2
      ],
      [
        0,
        2,
        3
      ],
      [],
      [
        0,
        2
      ],
      [
        0,
        1,
        2,
        3
      ]
    ],
    "behind": [
      [
        2
      ],
      [
        0,
        2,
        4
      ],
      [],
      [
        0,
        1,
        2,
        4
      ],
      [
        0,
        2
      ]
    ]
  },
  "split": "new",
  "image_index": 628,
  "objects": [
    {
      "3d_coords": [
        -0.2990695834159851,
        1.5449868440628052,
        0.3499999940395355
      ],
      "x": 177,
      "pixel_coords": [
        187,
        94,
        12.428281784057617
      ],
      "material": "metal",
      "size": "small",
      "width": 20,
      "height": 20,
      "color": "green",
      "y": 84,
      "shape": "sphere",
      "rotation": 29.70504858040082
    },
    {
      "3d_coords": [
        0.027137627825140953,
        -1.6043695211410522,
        0.699999988079071
      ],
      "x": 95,
      "pixel_coords": [
        120,
        117,
        10.192522048950195
      ],
      "material": "rubber",
      "size": "large",
      "width": 48,
      "height": 48,
      "color": "cyan",
      "y": 93,
      "shape": "sphere",
      "rotation": 138.10300223846951
    },
    {
      "3d_coords": [
        -0.2967107892036438,
        2.8629677295684814,
        0.699999988079071
      ],
      "x": 193,
      "pixel_coords": [
        212,
        76,
        13.034939765930176
      ],
      "material": "metal",
      "size": "large",
      "width": 38,
      "height": 38,
      "color": "green",
      "y": 57,
      "shape": "sphere",
      "rotation": 289.1753843032819
    },
    {
      "3d_coords": [
        1.8822593688964844,
        -2.236531972885132,
        0.699999988079071
      ],
      "x": 115,
      "pixel_coords": [
        144,
        152,
        8.6157808303833
      ],
      "material": "rubber",
      "size": "large",
      "width": 57,
      "height": 57,
      "color": "purple",
      "y": 123,
      "shape": "sphere",
      "rotation": 224.87812593669986
    },
    {
      "3d_coords": [
        -1.8235043287277222,
        -0.9156052470207214,
        0.3499999940395355
      ],
      "x": 93,
      "pixel_coords": [
        104,
        101,
        11.968079566955566
      ],
      "material": "metal",
      "size": "small",
      "width": 22,
      "height": 27,
      "color": "purple",
      "y": 87,
      "shape": "cylinder",
      "rotation": 356.4437701938714
    }
  ]
}