{
  "image_filename": "CLEVR_new_000405.png",
  "directions": {
    "above": [
      0.0,
      0.0,
      1.0
    ],
    "behind": [
      -0.754490315914154,
      0.6563112735748291,
      0.0
    ],
    "left": [
      -0.6563112735748291,
      -0.7544902563095093,
      0.0
    ],
    "below": [
      -0.0,
      -0.0,
      -1.0
    ],
    "right": [
      0.6563112735748291,
      0.7544902563095093,
      -0.0
    ],
    "front": [
      0.754490315914154,
      -0.6563112735748291,
      -0.0
    ]
  },
  "relationships": {
    "left": [
      [],
      [
        0,
        5
      ],
      [
        0,
        1,
        3,
        4,
        5
      ],
      [
        0,
        1,
        4,
        5
      ],
      [
        0,
        1,
        5
      ],
      [
        0
      ]
    ],
    "front": [
      [
        4,
        5
      ],
      [
        0,
        2,
        3,
        4,
        5
      ],
      [
        0,
        4,
        5
      ],
      [
        0,
        2,
        4,
        5
      ],
      [],
      [
        4
      ]
    ],
    "right": [
      [
        1,
        2,
        3,
        4,
        5
      ],
      [
        2,
        3,
        4
      ],
      [],
      [
        2
      ],
      [
        2,
        3
      ],
      [
        1,
        2,
        3,
        4
      ]
    ],
    "behind": [
      [
        1,
        2,
        3
      ],
      [],
      [
        1,
        3
      ],
      [
        1
      ],
      [
        0,
        1,
        2,
        3,
        5
      ],
      [
        0,
        1,
        2,
        3
      ]
    ]
  },
  "split": "new",
  "image_index": 405,
  "objects": [
    {
      "3d_coords": [
        -1.7490025758743286,
        -2.6300041675567627,
        0.3499999940395355
      ],
      "x": 43,
      "pixel_coords": [
        59,
        117,
        10.843628883361816
      ],
      "material": "metal",
      "size": "small",
      "width": 31,
      "height": 33,
      "color": "yellow",
      "y": 101,
      "shape": "cube",
      "rotation": 69.00224196846855
    },
    {
      "3d_coords": [
        -2.64340877532959,
        -0.003572793211787939,
        0.3499999940395355
      ],
      "x": 99,
      "pixel_coords": [
        112,
        86,
        12.961949348449707
      ],
      "material": "metal",
      "size": "small",
      "width": 26,
      "height": 26,
      "color": "cyan",
      "y": 73,
      "shape": "cube",
      "rotation": 270.3207082705519
    },
    {
      "3d_coords": [
        1.9266271591186523,
        2.9979729652404785,
        0.3499999940395355
      ],
      "x": 254,
      "pixel_coords": [
        265,
        103,
        11.719466209411621
      ],
      "material": "metal",
      "size": "small",
      "width": 22,
      "height": 21,
      "color": "gray",
      "y": 92,
      "shape": "sphere",
      "rotation": 79.43827505492867
    },
    {
      "3d_coords": [
        -0.1500989943742752,
        1.4324986934661865,
        0.3499999940395355
      ],
      "x": 178,
      "pixel_coords": [
        188,
        96,
        12.166508674621582
      ],
      "material": "metal",
      "size": "small",
      "width": 20,
      "height": 20,
      "color": "yellow",
      "y": 86,
      "shape": "sphere",
      "rotation": 212.08594760917845
    },
    {
      "3d_coords": [
        0.9429827332496643,
        -1.5941643714904785,
        0.3499999940395355
      ],
      "x": 124,
      "pixel_coords": [
        140,
        140,
        9.684520721435547
      ],
      "material": "rubber",
      "size": "small",
      "width": 30,
      "height": 35,
      "color": "brown",
      "y": 122,
      "shape": "cube",
      "rotation": 354.11307971436963
    },
    {
      "3d_coords": [
        -0.7624296545982361,
        -2.5057101249694824,
        0.3499999940395355
      ],
      "x": 62,
      "pixel_coords": [
        79,
        127,
        10.269861221313477
      ],
      "material": "metal",
      "size": "small",
      "width": 33,
      "height": 35,
      "color": "purple",
      "y": 110,
      "shape": "cube",
      "rotation": 177.4028505267923
    }
  ]
}