{
  "image_filename": "CLEVR_new_000522.png",
  "directions": {
    "above": [
      0.0,
      0.0,
      1.0
    ],
    "behind": [
      -0.754490315914154,
      0.6563112735748291,
      0.0
    ],
    "left": [
      -0.6563112735748291,
      -0.7544902563095093,
      0.0
    ],
    "below": [
      -0.0,
      -0.0,
      -1.0
    ],
    "right": [
      0.6563112735748291,
      0.7544902563095093,
      -0.0
    ],
    "front": [
      0.754490315914154,
      -0.6563112735748291,
      -0.0
    ]
  },
  "relationships": {
    "left": [
      [
        1,
        2,
        3
      ],
      [
        2
      ],
      [],
      [
        1,
        2
      ]
    ],
    "front": [
      [
        2
      ],
      [
        0,
        2
      ],
      [],
      [
        0,
        1,
        2
      ]
    ],
    "right": [
      [],
      [
        0,
        3
      ],
      [
        0,
        1,
        3
      ],
      [
        0
      ]
    ],
    "behind": [
      [
        1,
        3
      ],
      [
        3
      ],
      [
        0,
        1,
        3
      ],
      []
    ]
  },
  "split": "new",
  "image_index": 522,
  "objects": [
    {
      "3d_coords": [
        0.7116197943687439,
        0.1995539367198944,
        0.699999988079071
      ],
      "x": 156,
      "pixel_coords": [
        179,
        107,
        10.692459106445312
      ],
      "material": "metal",
      "size": "large",
      "width": 46,
      "height": 46,
      "color": "green",
      "y": 84,
      "shape": "sphere",
      "rotation": 144.5623857474774
    },
    {
      "3d_coords": [
        -1.7541687488555908,
        -0.781850278377533,
        0.699999988079071
      ],
      "x": 87,
      "pixel_coords": [
        110,
        89,
        11.864641189575195
      ],
      "material": "metal",
      "size": "large",
      "width": 47,
      "height": 55,
      "color": "red",
      "y": 62,
      "shape": "cube",
      "rotation": 76.53171572073553
    },
    {
      "3d_coords": [
        -0.7037655115127563,
        -2.4323928356170654,
        0.699999988079071
      ],
      "x": 45,
      "pixel_coords": [
        80,
        115,
        10.275093078613281
      ],
      "material": "rubber",
      "size": "large",
      "width": 66,
      "height": 65,
      "color": "green",
      "y": 84,
      "shape": "cube",
      "rotation": 303.870157878029
    },
    {
      "3d_coords": [
        -1.718900203704834,
        0.931053876876831,
        0.3499999940395355
      ],
      "x": 142,
      "pixel_coords": [
        152,
        86,
        12.919207572937012
      ],
      "material": "metal",
      "size": "small",
      "width": 19,
      "height": 19,
      "color": "green",
      "y": 76,
      "shape": "sphere",
      "rotation": 304.77681036308405
    }
  ]
}